{
   "cites":[
      {
         "id":"0",
         "city_name":"Kraków",
         "demand":0,
         "latitude":50.06143,
         "longitude":19.93658
      },
      {
         "id":"1",
         "city_name":"Białystok",
         "demand":500,
         "latitude":53.13333,
         "longitude":23.16433
      },
      {
         "id":"2",
         "city_name":"Bielsko-Biała",
         "demand":50,
         "latitude":49.82245,
         "longitude":19.04686
      },
      {
         "id":"3",
         "city_name":"Chrzanów",
         "demand":400,
         "latitude":50.13546,
         "longitude":19.40203
      },
      {
         "id":"4",
         "city_name":"Gdańsk",
         "demand":200,
         "latitude":54.35205,
         "longitude":18.64637
      },
      {
         "id":"5",
         "city_name":"Gdynia",
         "demand":100,
         "latitude":54.51889,
         "longitude":18.53188
      },
      {
         "id":"6",
         "city_name":"Gliwice",
         "demand":40,
         "latitude":50.29761,
         "longitude":18.67658
      },
      {
         "id":"7",
         "city_name":"Gromnik",
         "demand":200,
         "latitude":49.83843,
         "longitude":20.96123
      },
      {
         "id":"8",
         "city_name":"Katowice",
         "demand":300,
         "latitude":50.25841,
         "longitude":19.02754
      },
      {
         "id":"9",
         "city_name":"Kielce",
         "demand":30,
         "latitude":50.87033,
         "longitude":20.62752
      },
      {
         "id":"10",
         "city_name":"Krosno",
         "demand":60,
         "latitude":49.68866,
         "longitude":21.77058
      },
      {
         "id":"11",
         "city_name":"Krynica",
         "demand":50,
         "latitude":49.42225,
         "longitude":20.95942
      },
      {
         "id":"12",
         "city_name":"Lublin",
         "demand":60,
         "latitude":49.42225,
         "longitude":20.95942
      },
      {
         "id":"13",
         "city_name":"Łódź",
         "demand":160,
         "latitude":51.75,
         "longitude":19.46667
      },
      {
         "id":"14",
         "city_name":"Malbork",
         "demand":100,
         "latitude":54.03591,
         "longitude":19.0266
      },
      {
         "id":"15",
         "city_name":"Nowy Targ",
         "demand":120,
         "latitude":49.47783,
         "longitude":20.03228
      },
      {
         "id":"16",
         "city_name":"Olsztyn",
         "demand":300,
         "latitude":53.77995,
         "longitude":20.49416
      },
      {
         "id":"17",
         "city_name":"Poznań",
         "demand":100,
         "latitude":52.40692,
         "longitude":16.92993
      },
      {
         "id":"18",
         "city_name":"Puławy",
         "demand":200,
         "latitude":51.41655,
         "longitude":21.96939
      },
      {
         "id":"19",
         "city_name":"Radom",
         "demand":100,
         "latitude":51.40253,
         "longitude":21.14714
      },
      {
         "id":"20",
         "city_name":"Rzeszów",
         "demand":60,
         "latitude":50.04132,
         "longitude":21.99901
      },
      {
         "id":"21",
         "city_name":"Sandomierz",
         "demand":60,
         "latitude":50.68265,
         "longitude":21.74898
      },
      {
         "id":"22",
         "city_name":"Szczecin",
         "demand":150,
         "latitude":53.42894,
         "longitude":14.55302
      },
      {
         "id":"23",
         "city_name":"Szczucin",
         "demand":60,
         "latitude":50.309570,
         "longitude":21.074440
      },
      {
         "id":"24",
         "city_name":"Szklarska Poręba",
         "demand":50,
         "latitude":50.82567,
         "longitude":15.52274
      },
      {
         "id":"25",
         "city_name":"Tarnów",
         "demand":70,
         "latitude":50.01381,
         "longitude":20.98698
      },
      {
         "id":"26",
         "city_name":"Warszawa",
         "demand":200,
         "latitude":52.22977,
         "longitude":21.01178
      },
      {
         "id":"27",
         "city_name":"Wieliczka",
         "demand":90,
         "latitude":49.98738,
         "longitude":20.06473
      },
      {
         "id":"28",
         "city_name":"Wrocław",
         "demand":40,
         "latitude":51.1,
         "longitude":17.03333
      },
      {
         "id":"29",
         "city_name":"Zakopane",
         "demand":200,
         "latitude":49.29899,
         "longitude":19.94885
      },
      {
         "id":"30",
         "city_name":"Zamość",
         "demand":300,
         "latitude":50.72314,
         "longitude":23.25196
      }
   ]
}